tubing/__init__.py
tubing/apparatus.py
tubing/compat.py
tubing/sinks.py
tubing/sources.py
tubing/tubes.py
tubing/VERSION
tubing/ext/__init__.py
tubing/ext/elasticsearch.py
tubing/ext/postgres.py
tubing/ext/s3.py
tubing-0.0.2.post180.dist-info/top_level.txt
tubing-0.0.2.post180.dist-info/METADATA
tubing-0.0.2.post180.dist-info/DESCRIPTION.rst
tubing-0.0.2.post180.dist-info/metadata.json
tubing-0.0.2.post180.dist-info/WHEEL
tubing-0.0.2.post180.dist-info/RECORD
