Metadata-Version: 2.0
Name: tubing
Version: 0.0.2.post180
Summary: Python I/O pipe utilities
Home-page: http://github.com/dokipen/tubing
Author: Bob Corsaro
Author-email: rcorsaro@gmail.com
License: MIT
Platform: UNKNOWN
Classifier: Development Status :: 3 - Alpha
Classifier: Intended Audience :: Developers
Classifier: License :: OSI Approved :: MIT License
Classifier: Programming Language :: Python
Classifier: Programming Language :: Python :: 2.6
Classifier: Programming Language :: Python :: 2.7
Classifier: Programming Language :: Python :: 3.2
Classifier: Programming Language :: Python :: 3.3
Classifier: Programming Language :: Python :: 3.4
Classifier: Programming Language :: Python :: 3.5
Classifier: Programming Language :: Python :: Implementation :: CPython
Classifier: Programming Language :: Python :: Implementation :: PyPy
Requires-Dist: requests
Requires-Dist: urllib3
Provides-Extra: build
Requires-Dist: yapf; extra == 'build'
Requires-Dist: pyflakes; extra == 'build'
Requires-Dist: nose; extra == 'build'
Requires-Dist: unittest2; extra == 'build'
Requires-Dist: coveralls; extra == 'build'
Requires-Dist: boto3; extra == 'build'
Provides-Extra: docs
Requires-Dist: sphinx; extra == 'docs'
Requires-Dist: sphinx-rtd-theme; extra == 'docs'
Provides-Extra: elasticsearch
Provides-Extra: s3
Requires-Dist: boto3; extra == 's3'
Provides-Extra: ujson
Requires-Dist: ujson; extra == 'ujson'
